handy/AsciiString.py
handy/CIDict.py
handy/CIString.py
handy/ProgInfo.py
handy/Spinner.py
handy/__init__.py
jc_handy_helpers-1.1.0.dist-info/licenses/LICENSE
jc_handy_helpers-1.1.0.dist-info/METADATA
jc_handy_helpers-1.1.0.dist-info/WHEEL
jc_handy_helpers-1.1.0.dist-info/top_level.txt
jc_handy_helpers-1.1.0.dist-info/RECORD
