Metadata-Version: 2.4
Name: jc-handy-helpers
Version: 1.1.0
Summary: A collection of useful Python classes and functions.
Author-email: Jeff Clough <jeff@cloughcottage.com>
License: MIT License
Project-URL: Homepage, https://github.com/jc-handy/handy
Keywords: utility,toolkit,convenience
Classifier: Development Status :: 5 - Production/Stable
Classifier: Intended Audience :: Developers
Classifier: License :: OSI Approved :: MIT License
Classifier: Programming Language :: Python :: 3
Classifier: Programming Language :: Python :: 3.11
Classifier: Operating System :: OS Independent
Requires-Python: >=3.11
License-File: LICENSE
Dynamic: license-file
